itom_library/__init__.py
itom_library/oo_client.py
itom_library/py.typed
itom_library/utilities.py
itom_library-0.1.0.dist-info/METADATA
itom_library-0.1.0.dist-info/WHEEL
itom_library-0.1.0.dist-info/licenses/LICENSE
itom_library-0.1.0.dist-info/RECORD
