Metadata-Version: 2.4
Name: itom-library
Version: 0.1.0
Summary: A Python client library for ITOM
License: MIT
License-File: LICENSE
Requires-Python: >=3.10
Requires-Dist: requests>=2.28.0
Provides-Extra: dev
Requires-Dist: pytest>=7.0.0; extra == 'dev'
Requires-Dist: responses>=0.23.0; extra == 'dev'
